{"total":5,"pageSize":12,"pageCount":1,"data":[{"title":"「仰望天空，注视天空，答案就在那里」","uid":"3eee49349866b18cfb889f5668f42b14","slug":"Galgame_Aokana_Asuka","date":"2026-01-20T15:00:00.000Z","updated":"2026-01-20T16:00:27.358Z","comments":true,"path":"api/articles/Galgame_Aokana_Asuka.json","keywords":null,"cover":"https://blogmeowwow520cn.oss-cn-beijing.aliyuncs.com/hexo/source/img/Cover/Galgame_Aokana-Asuka.jpg","text":"仓科明日香: 所以，我希望你能教我更多，让我能更开心地飞...","permalink":"/post/Galgame_Aokana_Asuka","photos":[],"count_time":{"symbolsCount":"3.2k","symbolsTime":"3 mins."},"categories":[],"tags":[{"name":"Galgame","slug":"Galgame","count":1,"path":"api/tags/Galgame.json"}],"author":{"name":"MeowWow520","slug":"blog-author","avatar":"https://blogmeowwow520cn.oss-cn-beijing.aliyuncs.com/hexo/source/img/MyHander.jpg","link":"https://blog.meowwow520.cn/","description":"Some says this place is where you can mine gold and diamonds! Everything I Want Wants Me Too.","socials":{}},"feature":true},{"title":"2026年度追番列表","uid":"7ebd1c3ce884d84fd50383c04571f806","slug":"Anime_2026AnnualList","date":"2026-01-14T16:00:00.000Z","updated":"2026-01-20T16:02:46.545Z","comments":true,"path":"api/articles/Anime_2026AnnualList.json","keywords":null,"cover":"https://blogmeowwow520cn.oss-cn-beijing.aliyuncs.com/hexo/source/img/Cover/Anime_2026AnnualList.jpg","text":"2026年我都追了那些番剧？...","permalink":"/post/Anime_2026AnnualList","photos":[],"count_time":{"symbolsCount":71,"symbolsTime":"1 mins."},"categories":[],"tags":[{"name":"Anime","slug":"Anime","count":1,"path":"api/tags/Anime.json"},{"name":"Annual List","slug":"Annual-List","count":1,"path":"api/tags/Annual-List.json"}],"author":{"name":"MeowWow520","slug":"blog-author","avatar":"https://blogmeowwow520cn.oss-cn-beijing.aliyuncs.com/hexo/source/img/MyHander.jpg","link":"https://blog.meowwow520.cn/","description":"Some says this place is where you can mine gold and diamonds! Everything I Want Wants Me Too.","socials":{}},"feature":true},{"title":"借助内网穿透在 Minecraft 中联机(速通版)","uid":"9b3de41fa95281100d9c3ed956cec458","slug":"UsingFrpOpenAMcServer","date":"2025-12-14T07:00:00.000Z","updated":"2025-12-18T08:01:04.359Z","comments":true,"path":"api/articles/UsingFrpOpenAMcServer.json","keywords":null,"cover":"https://blogmeowwow520cn.oss-cn-beijing.aliyuncs.com/hexo/source/img/Cover/UsingFrpOpenAMcServer.png","text":"本文章介绍了如何借助内网穿透技术在 Minecraft 中与异地好友联机。...","permalink":"/post/UsingFrpOpenAMcServer","photos":[],"count_time":{"symbolsCount":"1.6k","symbolsTime":"1 mins."},"categories":[],"tags":[{"name":"Minecraft","slug":"Minecraft","count":2,"path":"api/tags/Minecraft.json"},{"name":"MC Server","slug":"MC-Server","count":1,"path":"api/tags/MC-Server.json"},{"name":"教程","slug":"教程","count":2,"path":"api/tags/教程.json"}],"author":{"name":"MeowWow520","slug":"blog-author","avatar":"https://blogmeowwow520cn.oss-cn-beijing.aliyuncs.com/hexo/source/img/MyHander.jpg","link":"https://blog.meowwow520.cn/","description":"Some says this place is where you can mine gold and diamonds! Everything I Want Wants Me Too.","socials":{}},"feature":true},{"title":"正版 Minecraft 的购买","uid":"3096d7d55ce8b45f70588a18ee0f3f4f","slug":"HowToBuyAMinecraft","date":"2025-12-13T07:00:00.000Z","updated":"2025-12-18T08:01:01.677Z","comments":true,"path":"api/articles/HowToBuyAMinecraft.json","keywords":null,"cover":"https://blogmeowwow520cn.oss-cn-beijing.aliyuncs.com/hexo/source/img/Cover/HowToBuyAMinecraft.jpg","text":"本文章为各位 Minecraft 新玩家提供购买的教程...","permalink":"/post/HowToBuyAMinecraft","photos":[],"count_time":{"symbolsCount":"3.2k","symbolsTime":"3 mins."},"categories":[],"tags":[{"name":"Minecraft","slug":"Minecraft","count":2,"path":"api/tags/Minecraft.json"},{"name":"教程","slug":"教程","count":2,"path":"api/tags/教程.json"}],"author":{"name":"MeowWow520","slug":"blog-author","avatar":"https://blogmeowwow520cn.oss-cn-beijing.aliyuncs.com/hexo/source/img/MyHander.jpg","link":"https://blog.meowwow520.cn/","description":"Some says this place is where you can mine gold and diamonds! Everything I Want Wants Me Too.","socials":{}},"feature":false},{"title":"About Me","uid":"fafbaf41596ea98d4569aecf909ab64f","slug":"AboutMe","date":"2024-12-31T03:00:00.000Z","updated":"2025-12-18T08:01:15.549Z","comments":true,"path":"api/articles/AboutMe.json","keywords":null,"cover":"https://blogmeowwow520cn.oss-cn-beijing.aliyuncs.com/hexo/source/img/Cover/AboutMe.jpg","text":"Some says this place is where you can mine gold and diamonds!...","permalink":"/post/AboutMe","photos":[],"count_time":{"symbolsCount":936,"symbolsTime":"1 mins."},"categories":[],"tags":[{"name":"AboutMe","slug":"AboutMe","count":1,"path":"api/tags/AboutMe.json"}],"author":{"name":"MeowWow520","slug":"blog-author","avatar":"https://blogmeowwow520cn.oss-cn-beijing.aliyuncs.com/hexo/source/img/MyHander.jpg","link":"https://blog.meowwow520.cn/","description":"Some says this place is where you can mine gold and diamonds! Everything I Want Wants Me Too.","socials":{}},"feature":false}]}