{"title":"Welcome To Here","type":"page","uid":"51fc2fb2bd8aba1427e299d158bb44c6","text":"我是谁？我是一个拥有梦想但从未实行的高三毕业生。 为什么会有这个博客？ 即将来临的一天，比过去的一年都更为悠长。————【德】布莱希特 尽管我对未来很期待，但我也时常回想过去式。我回忆以前，那是我成长的过程。但……显而易见，我回不去了。宇宙给予了时间不可逆的性质，但我却想：如何“...","date":"2024-06-16T13:00:00.000Z","updated":"2024-06-17T04:35:44.006Z","comments":true,"path":"api/pages/about/index.json","covers":null,"excerpt":"","content":"<h1 id=\"我是谁？\"><a href=\"#我是谁？\" class=\"headerlink\" title=\"我是谁？\"></a>我是谁？</h1><p>我是一个拥有梦想但<strong>从未</strong>实行的高三毕业生。</p>\n<h1 id=\"为什么会有这个博客？\"><a href=\"#为什么会有这个博客？\" class=\"headerlink\" title=\"为什么会有这个博客？\"></a>为什么会有这个博客？</h1><blockquote><span class=\"custom-blockquote-svg\"><svg width=\"24\" height=\"24\" viewBox=\"0 0 24 24\" fill=\"\" xmlns=\"http://www.w3.org/2000/svg\" data-reactroot=\"\">\n<path fill=\"\" d=\"M22 12C22 6.5 17.5 2 12 2C6.5 2 2 6.5 2 12C2 17.5 6.5 22 12 22C13.8 22 15.5 21.5 17 20.6L22 22L20.7 17C21.5 15.5 22 13.8 22 12Z\" undefined=\"1\"></path>\n<path fill=\"\" d=\"M15.97 11.5H16.04C17.12 11.5 18 12.38 18 13.47V13.53C18 14.62 17.12 15.5 16.03 15.5H15.96C14.88 15.5 14 14.62 14 13.53V13.46C14 12.38 14.88 11.5 15.97 11.5Z\" undefined=\"1\"></path>\n<path fill=\"\" d=\"M7.97 11.5H8.04C9.12 11.5 10 12.38 10 13.47V13.53C10 14.62 9.12 15.5 8.03 15.5H7.97C6.88 15.5 6 14.62 6 13.53V13.46C6 12.38 6.88 11.5 7.97 11.5Z\" undefined=\"1\"></path>\n<path stroke-linejoin=\"round\" stroke-linecap=\"round\" stroke-miterlimit=\"10\" stroke-width=\"2\" stroke=\"\" d=\"M17 8.5C15.23 8.97 14.07 10.84 14.01 13.27C14 13.33 14 13.4 14 13.47V13.5\"></path>\n<path stroke-linejoin=\"round\" stroke-linecap=\"round\" stroke-miterlimit=\"10\" stroke-width=\"2\" stroke=\"\" d=\"M9 8.5C7.23 8.97 6.07 10.84 6.01 13.27C6 13.33 6 13.4 6 13.47V13.5\"></path>\n<path stroke-linejoin=\"round\" stroke-linecap=\"round\" stroke-miterlimit=\"10\" stroke-width=\"2\" stroke=\"\" d=\"M15.97 11.5H16.04C17.12 11.5 18 12.38 18 13.47V13.53C18 14.62 17.12 15.5 16.03 15.5H15.96C14.88 15.5 14 14.62 14 13.53V13.46C14 12.38 14.88 11.5 15.97 11.5Z\"></path>\n<path stroke-linejoin=\"round\" stroke-linecap=\"round\" stroke-miterlimit=\"10\" stroke-width=\"2\" stroke=\"\" d=\"M7.97 11.5H8.04C9.12 11.5 10 12.38 10 13.47V13.53C10 14.62 9.12 15.5 8.03 15.5H7.97C6.88 15.5 6 14.62 6 13.53V13.46C6 12.38 6.88 11.5 7.97 11.5Z\"></path>\n</svg>\n</span><p>即将来临的一天，比过去的一年都更为悠长。————【德】<em>布莱希特</em></p></blockquote>\n<p>尽管我对未来很期待，但我也时常回想过去式。我回忆以前，那是我成长的过程。但……<br>显而易见，我回不去了。<br>宇宙给予了时间不可逆的性质，但我却想：<em>如何“回到”过去？</em><br>终于，2023年我发现了它————<a href=\"https://hexo.io/zh-cn/\" title=\"Hexo官方\">Hexo</a><br>它帮助了我这个初学者入门自己制作一个博客。<br>所以我学习了<del>很长时间</del>做了这个博客（也没多长，高三嘛。dddd）</p>\n<h1 id=\"这个博客的作用\"><a href=\"#这个博客的作用\" class=\"headerlink\" title=\"这个博客的作用\"></a>这个博客的作用</h1><p><strong>首先</strong><br>给我回忆，前面提到“宇宙给予了时间不可逆的性质，但我却想：<em>如何‘回到’过去？</em>”<br>所以我会把自己人生中精彩的时刻在此记录下来，还请期待<br><strong>其次</strong><br>让别人了解我。我的圈子并不大，我希望通过博客让更多人知道我的存在。<br><del>话说有人看吗？！</del><br><strong>最后</strong><br>一个字：装</p>\n<h1 id=\"我对这个博客的期望\"><a href=\"#我对这个博客的期望\" class=\"headerlink\" title=\"我对这个博客的期望\"></a>我对这个博客的期望</h1><p>我希望它真的可以起到回忆的目的。<br>我并不强求它可以为我带来什么<br>我只希望我会坚持到底，哪怕若干年后曾经来过的人忘记了这个博客</p>\n<h1 id=\"最后的话\"><a href=\"#最后的话\" class=\"headerlink\" title=\"最后的话\"></a>最后的话</h1><p><strong>勿忘以往</strong></p>\n","count_time":{"symbolsCount":432,"symbolsTime":"1 mins."},"toc":"<ol class=\"toc\"><li class=\"toc-item toc-level-1\"><a class=\"toc-link\" href=\"#%E6%88%91%E6%98%AF%E8%B0%81%EF%BC%9F\"><span class=\"toc-text\">我是谁？</span></a></li><li class=\"toc-item toc-level-1\"><a class=\"toc-link\" href=\"#%E4%B8%BA%E4%BB%80%E4%B9%88%E4%BC%9A%E6%9C%89%E8%BF%99%E4%B8%AA%E5%8D%9A%E5%AE%A2%EF%BC%9F\"><span class=\"toc-text\">为什么会有这个博客？</span></a></li><li class=\"toc-item toc-level-1\"><a class=\"toc-link\" href=\"#%E8%BF%99%E4%B8%AA%E5%8D%9A%E5%AE%A2%E7%9A%84%E4%BD%9C%E7%94%A8\"><span class=\"toc-text\">这个博客的作用</span></a></li><li class=\"toc-item toc-level-1\"><a class=\"toc-link\" href=\"#%E6%88%91%E5%AF%B9%E8%BF%99%E4%B8%AA%E5%8D%9A%E5%AE%A2%E7%9A%84%E6%9C%9F%E6%9C%9B\"><span class=\"toc-text\">我对这个博客的期望</span></a></li><li class=\"toc-item toc-level-1\"><a class=\"toc-link\" href=\"#%E6%9C%80%E5%90%8E%E7%9A%84%E8%AF%9D\"><span class=\"toc-text\">最后的话</span></a></li></ol>","data":[]}